openresearch/__init__.py
openresearch/openresearch.py
ormigrate/EventLocationHandler.py
ormigrate/__init__.py
ormigrate/dictionary.py
ormigrate/fixer.py
ormigrate/issue119_ordinal.py
ormigrate/issue136_MissingAcronym.py
ormigrate/issue150_nullvalue.py
ormigrate/issue152_acceptancerate.py
ormigrate/issue163_series.py
ormigrate/issue166_cfp.py
ormigrate/issue170_curation.py
ormigrate/issue195_biblographic.py
ormigrate/issue211_year.py
ormigrate/issue220_location.py
ormigrate/issue228_country.py
ormigrate/issue256_cfpSeries.py
ormigrate/issue41_acronym.py
ormigrate/issue57_eventSeriesProvenanceFixer.py
ormigrate/issue71_date.py
ormigrate/toolbox.py
ormigrate/resources/dictionary.yaml
ormigrate/resources/queries.yaml
ormigrate/resources/userrating.yaml
ormigrate/resources/templates/location/template_page.jinja
ormigrate/resources/topics/event.json
ormigrate/resources/topics/eventSeries.json
ormigrate/resources/topics/fixer.json
ormigrate/resources/topics/location.json
ormigrate/resources/topics/rating.json
ormigrate/smw/__init__.py
ormigrate/smw/pagefixer.py
ormigrate/smw/rating.py
ormigrate/smw/templates.py
OpenResearchMigration-0.0.30.dist-info/METADATA
OpenResearchMigration-0.0.30.dist-info/WHEEL
OpenResearchMigration-0.0.30.dist-info/entry_points.txt
OpenResearchMigration-0.0.30.dist-info/top_level.txt
OpenResearchMigration-0.0.30.dist-info/RECORD
