Metadata-Version: 2.1
Name: OpenResearchMigration
Version: 0.0.30
Summary: python api to access OPENRESEARCH data
Home-page: https://www.openresearch.org/wiki/Main_Page
Author: Wolfgang Fahl
Author-email: wf@bitplan.com
License: Apache
Download-URL: https://github.com/SmartDataAnalytics/OpenResearch
Project-URL: Code, https://github.com/SmartDataAnalytics/OpenResearch
Project-URL: Issue tracker, https://github.com/SmartDataAnalytics/OpenResearch/issues
Platform: UNKNOWN
Classifier: Programming Language :: Python
Classifier: Programming Language :: Python :: 3.7
Classifier: Programming Language :: Python :: 3.8
Classifier: Programming Language :: Python :: 3.9
Requires-Dist: pylodstorage
Requires-Dist: python-dateutil
Requires-Dist: py-3rdparty-mediawiki
Requires-Dist: wikitextparser
Requires-Dist: geograpy3
Requires-Dist: ConferenceCorpus
Requires-Dist: OSMPythonTools
